helloworld.py
cvdscorer-0.0.1.dist-info/LICENSE
cvdscorer-0.0.1.dist-info/METADATA
cvdscorer-0.0.1.dist-info/WHEEL
cvdscorer-0.0.1.dist-info/top_level.txt
cvdscorer-0.0.1.dist-info/RECORD
