Metadata-Version: 2.1
Name: cvdscorer
Version: 0.0.1
Summary: Tool to calculate cardio-vascular disease risk
Home-page: https://github.com/PeterPirog/CVDScorer
Author: Peter Pirog
Author-email: peterpirogtf@gmail.com
Classifier: Programming Language :: Python :: 3
Classifier: Programming Language :: Python :: 3.6
Classifier: Programming Language :: Python :: 3.7
Classifier: Programming Language :: Python :: 3.8
Classifier: Programming Language :: Python :: 3.9
Classifier: Programming Language :: Python :: 3.10
Classifier: Programming Language :: Python :: 3.11
Classifier: License :: OSI Approved :: GNU General Public License v2 or later (GPLv2+)
Classifier: Operating System :: OS Independent
License-File: LICENSE
Requires-Dist: pandas (>=1)
Provides-Extra: dev
Requires-Dist: pytest (>=3.7) ; extra == 'dev'
